editdistpy-0.1.6.dist-info/top_level.txt
editdistpy-0.1.6.dist-info/RECORD
editdistpy-0.1.6.dist-info/METADATA
editdistpy-0.1.6.dist-info/WHEEL
editdistpy-0.1.6.dist-info/licenses/LICENSE
editdistpy/damerau_osa.cpython-312-x86_64-linux-gnu.so
editdistpy/levenshtein.pyx
editdistpy/damerau_osa.pyx
editdistpy/levenshtein.cpython-312-x86_64-linux-gnu.so
editdistpy/_levenshtein.h
editdistpy/levenshtein.pyi
editdistpy/__init__.py
editdistpy/_damerau_osa.cpp
editdistpy/_levenshtein.cpp
editdistpy/_helpers.h
editdistpy/_damerau_osa.h
editdistpy/damerau_osa.cpp
editdistpy/levenshtein.cpp
editdistpy/_def.h
editdistpy/damerau_osa.pyi
