Metadata-Version: 2.4
Name: editdistpy
Version: 0.1.6
Summary: Fast Levenshtein and Damerau optimal string alignment algorithms.
Author: mmb L
License-Expression: MIT
Project-URL: Repository, https://github.com/mammothb/editdistpy
Project-URL: Changelog, https://github.com/mammothb/editdistpy/blob/master/CHANGELOG.md
Keywords: edit distance,levenshtein,damerau
Classifier: Development Status :: 4 - Beta
Classifier: Intended Audience :: Developers
Classifier: Intended Audience :: Science/Research
Classifier: Natural Language :: English
Classifier: Operating System :: Microsoft :: Windows
Classifier: Operating System :: POSIX
Classifier: Operating System :: Unix
Classifier: Operating System :: MacOS
Classifier: Programming Language :: C++
Classifier: Programming Language :: Cython
Classifier: Programming Language :: Python
Classifier: Programming Language :: Python :: 3
Classifier: Programming Language :: Python :: 3.9
Classifier: Programming Language :: Python :: 3.10
Classifier: Programming Language :: Python :: 3.11
Classifier: Programming Language :: Python :: 3.12
Classifier: Programming Language :: Python :: 3.13
Classifier: Programming Language :: Python :: Implementation :: CPython
Requires-Python: >=3.9
License-File: LICENSE
Dynamic: license-file
